<?xml version="1.0" encoding="UTF-8"?>
<build-type xmlns:xsi="http://www.w3.org/2001/XMLSchema-instance" uuid="c423f307-1cd4-4b20-ba43-f3c4e685c319" xsi:noNamespaceSchemaLocation="http://www.jetbrains.com/teamcity/schemas/10.0/project-config.xsd">
  <name>Build x86</name>
  <description />
  <settings ref="PizzaCalculator_Build">
    <disabled-settings>
      <setting-ref ref="RUNNER_2" />
    </disabled-settings>
    <parameters />
    <build-runners order="RUNNER_1, RUNNER_2, RUNNER_7, RUNNER_3, RUNNER_4">
      <runner id="RUNNER_7" name="Build x86" type="dotnet">
        <parameters>
          <param name="dotNetCoverage.dotCover.home.path" value="%teamcity.tool.JetBrains.dotCover.CommandLineTools.DEFAULT%" />
          <param name="dotnet-build-config" value="Release" />
          <param name="dotnet-build-runtime" value="win-x86" />
          <param name="dotnet-command" value="build" />
          <param name="dotnet-paths" value="src/pizza-calculator.csproj" />
          <param name="teamcity.step.mode" value="default" />
        </parameters>
      </runner>
    </build-runners>
    <vcs-settings />
    <requirements />
    <build-triggers />
    <cleanup />
  </settings>
</build-type>

